PWSH/PWSH.py
PWSH/__init__.py
PWSH_Astremy_1-1.3.3.dist-info/LICENSE
PWSH_Astremy_1-1.3.3.dist-info/METADATA
PWSH_Astremy_1-1.3.3.dist-info/WHEEL
PWSH_Astremy_1-1.3.3.dist-info/top_level.txt
PWSH_Astremy_1-1.3.3.dist-info/RECORD
