Metadata-Version: 2.1
Name: PWSH-Astremy-1
Version: 1.3.3
Summary: A framework to help for backend
Home-page: https://github.com/Astremy/Python-Web-Site-Helper
Author: Astremy
Author-email: 
License: UNKNOWN
Platform: UNKNOWN
Classifier: Programming Language :: Python :: 3
Classifier: License :: OSI Approved :: MIT License
Classifier: Operating System :: OS Independent
Requires-Python: >=3.6
